{
  "exchanges": {
    "binance": {
      "error": null,
      "pair_count": 1366,
      "pairs_sample": [
        "ETHBTC",
        "LTCBTC",
        "BNBBTC",
        "BNBETH",
        "BTCUSDT",
        "ETHUSDT",
        "LINKBTC",
        "LINKETH",
        "ETCBTC",
        "ZECBTC"
      ]
    },
    "bybit": {
      "error": null,
      "pair_count": 592,
      "pairs_sample": [
        "BTCUSDT",
        "ETHUSDT",
        "XRPUSDT",
        "ETHBTC",
        "XRPBTC",
        "DOTUSDT",
        "XLMUSDT",
        "LTCUSDT",
        "DOGEUSDT",
        "CHZUSDT"
      ]
    },
    "coinbase": {
      "error": null,
      "pair_count": 527,
      "pairs_sample": [
        "PAX-USD",
        "RAY-USD",
        "TNSR-USD",
        "PNUT-USD",
        "LINK-ETH",
        "MASK-GBP",
        "SIGN-USD",
        "PUMP-USD",
        "1INCH-EUR",
        "KRL-USD"
      ]
    },
    "kraken": {
      "error": null,
      "pair_count": 1407,
      "pairs_sample": [
        "0GEUR",
        "0GUSD",
        "1INCHEUR",
        "1INCHUSD",
        "2ZEUR",
        "2ZUSD",
        "AAVEETH",
        "AAVEEUR",
        "AAVEGBP",
        "AAVEUSD"
      ]
    },
    "okx": {
      "error": null,
      "pair_count": 1308,
      "pairs_sample": [
        "USDC-TEV",
        "USDT-SGD",
        "USDC-SGD",
        "USDG-SGD",
        "BTC-AUD",
        "ETH-AUD",
        "SOL-AUD",
        "XRP-AUD",
        "AUDF-AUD",
        "AUDM-AUD"
      ]
    }
  },
  "generated_at": "2026-07-21T03:33:37.171130+00:00",
  "snapshot_date": "2026-07-21"
}