{
  "exchanges": {
    "binance": {
      "error": null,
      "status": {
        "api_latency_ms": 241,
        "error": null,
        "exchange": "binance",
        "healthy": true,
        "raw": {},
        "spot_pair_count": 1359
      }
    },
    "bybit": {
      "error": null,
      "status": {
        "api_latency_ms": 185,
        "error": null,
        "exchange": "bybit",
        "healthy": true,
        "raw": {},
        "spot_pair_count": 602
      }
    },
    "coinbase": {
      "error": null,
      "status": {
        "api_latency_ms": 131,
        "error": null,
        "exchange": "coinbase",
        "healthy": true,
        "raw": {},
        "spot_pair_count": 526
      }
    },
    "kraken": {
      "error": null,
      "status": {
        "api_latency_ms": 43,
        "error": null,
        "exchange": "kraken",
        "healthy": true,
        "raw": {
          "system_status": "online"
        },
        "spot_pair_count": 1421
      }
    },
    "okx": {
      "error": null,
      "status": {
        "api_latency_ms": 212,
        "error": null,
        "exchange": "okx",
        "healthy": true,
        "raw": {},
        "spot_pair_count": 1273
      }
    }
  },
  "generated_at": "2026-06-27T04:10:53.204663+00:00",
  "snapshot_date": "2026-06-27"
}